zdxtools/__init__.py
zdxtools/dx_tools.py
zdxtools/setup.py
zdxtools/AutoGui/AutoGui.py
zdxtools/AutoGui/__init__.py
zdxtools/ctypes/__init__.py
zdxtools/ctypes/copy_struct_generic.py
zdxtools/decorator/__init__.py
zdxtools/decorator/decorator.py
zdxtools/dx_img/__init__.py
zdxtools/dx_img/dx_img.py
zdxtools/dx_os/__init__.py
zdxtools/dx_os/dx_os.py
zdxtools/math/__init__.py
zdxtools/math/math_tools.py
zdxtools/math_tools/__init__.py
zdxtools/math_tools/math_tools.py
zdxtools/pics/__init__.py
zdxtools/pics/compress_png.py
zdxtools/pics/convert_pic_to_webp.py
zdxtools/pics/convert_webp_to_jpg.py
zdxtools/process/GetProcessNameByCtype.py
zdxtools/process/__init__.py
zdxtools/process/find_and_kill_process_by_port.py
zdxtools/process/find_pid_by_name.py
zdxtools/process/kill_process_by_pid.py
zdxtools/process/run_as_admin.py
zdxtools/source/__init__.py
zdxtools/source/stealth.min.js
zdxtools/spider_tools/__init__.py
zdxtools/spider_tools/spider_tools.py
zdxtools/winrar/__init__.py
zdxtools/winrar/comment.txt
zdxtools/winrar/comment_card.txt
zdxtools/winrar/winrar_yasuo.py
zdxtools/winrar/winrar_yasuo_setting.py
zdxtools-0.0.33.dist-info/LICENSE
zdxtools-0.0.33.dist-info/METADATA
zdxtools-0.0.33.dist-info/WHEEL
zdxtools-0.0.33.dist-info/top_level.txt
zdxtools-0.0.33.dist-info/RECORD
