Metadata-Version: 2.1
Name: zdxtools
Version: 0.0.33
Summary: 包含图形处理，OS处理，爬虫处理，加密的日常封装
Home-page: https://github.com/pypa/sampleproject
Author: zhou
Author-email: 1057129097@qq.com
Project-URL: Bug Tracker, https://github.com/pypa/sampleproject/issues
Classifier: Programming Language :: Python :: 3
Classifier: License :: OSI Approved :: MIT License
Classifier: Operating System :: OS Independent
Requires-Python: >=3.6
License-File: LICENSE
